[
  {
    "timestamp": "2025-06-28T13:28:18.381093",
    "user": "system",
    "activity": "Navigated to: Log Aktivitas",
    "details": {}
  },
  {
    "timestamp": "2025-06-28T13:28:31.931471",
    "user": "system",
    "activity": "Navigated to: Input Stock Obat",
    "details": {}
  },
  {
    "timestamp": "2025-06-28T13:29:25.274796",
    "user": "system",
    "activity": "Navigated to: Input Stock Obat",
    "details": {}
  },
  {
    "timestamp": "2025-06-28T13:29:30.677209",
    "user": "system",
    "activity": "Navigated to: Input Stock Obat",
    "details": {}
  },
  {
    "timestamp": "2025-06-28T13:29:33.897488",
    "user": "system",
    "activity": "Navigated to: Daftar Obat",
    "details": {}
  },
  {
    "timestamp": "2025-06-28T13:29:34.807629",
    "user": "system",
    "activity": "Navigated to: Input Data Resep Obat",
    "details": {}
  },
  {
    "timestamp": "2025-06-28T13:29:35.823258",
    "user": "system",
    "activity": "Navigated to: Daftar Obat",
    "details": {}
  },
  {
    "timestamp": "2025-06-28T13:29:36.369431",
    "user": "system",
    "activity": "Navigated to: Input Stock Obat",
    "details": {}
  },
  {
    "timestamp": "2025-06-28T13:30:33.478482",
    "user": "system",
    "activity": "Navigated to: Manajemen Data Obat",
    "details": {}
  },
  {
    "timestamp": "2025-06-28T13:31:34.581644",
    "user": "system",
    "activity": "Navigated to: Input Data Resep Obat",
    "details": {}
  },
  {
    "timestamp": "2025-06-28T13:31:35.800972",
    "user": "system",
    "activity": "Navigated to: Proses Analisis ECLAT",
    "details": {}
  },
  {
    "timestamp": "2025-06-28T13:31:36.595712",
    "user": "system",
    "activity": "Navigated to: Lihat Hasil Analisis",
    "details": {}
  },
  {
    "timestamp": "2025-06-28T13:31:37.211804",
    "user": "system",
    "activity": "Navigated to: Input Data Resep Obat",
    "details": {}
  },
  {
    "timestamp": "2025-06-28T13:31:37.753281",
    "user": "system",
    "activity": "Navigated to: Manajemen Data Obat",
    "details": {}
  },
  {
    "timestamp": "2025-06-28T13:31:48.556772",
    "user": "system",
    "activity": "Navigated to: Manajemen Data Obat",
    "details": {}
  },
  {
    "timestamp": "2025-06-28T13:31:49.610952",
    "user": "system",
    "activity": "Navigated to: Manajemen Data Obat",
    "details": {}
  },
  {
    "timestamp": "2025-06-28T13:31:51.323643",
    "user": "system",
    "activity": "Navigated to: Manajemen Data Obat",
    "details": {}
  },
  {
    "timestamp": "2025-06-28T13:32:09.500154",
    "user": "system",
    "activity": "Navigated to: Manajemen Data Obat",
    "details": {}
  },
  {
    "timestamp": "2025-06-28T13:32:21.177279",
    "user": "system",
    "activity": "Navigated to: Manajemen Data Obat",
    "details": {}
  },
  {
    "timestamp": "2025-06-28T13:51:33.314071",
    "user": "system",
    "activity": "Navigated to: Manajemen Data Obat",
    "details": {}
  },
  {
    "timestamp": "2025-07-01T22:56:22.238010",
    "user": "system",
    "activity": "Navigated to: Manajemen Data Obat",
    "details": {}
  },
  {
    "timestamp": "2025-07-01T22:56:34.630672",
    "user": "system",
    "activity": "Navigated to: Input Data Resep Obat",
    "details": {}
  },
  {
    "timestamp": "2025-07-01T22:56:35.718745",
    "user": "system",
    "activity": "Navigated to: Proses Analisis ECLAT",
    "details": {}
  },
  {
    "timestamp": "2025-07-01T22:56:36.801788",
    "user": "system",
    "activity": "Navigated to: Lihat Hasil Analisis",
    "details": {}
  },
  {
    "timestamp": "2025-07-01T22:56:37.592194",
    "user": "system",
    "activity": "Navigated to: Lihat Rekomendasi Obat",
    "details": {}
  },
  {
    "timestamp": "2025-07-01T22:56:38.301212",
    "user": "system",
    "activity": "Navigated to: Unduh Laporan",
    "details": {}
  },
  {
    "timestamp": "2025-07-01T22:56:38.830413",
    "user": "system",
    "activity": "Navigated to: Log Aktivitas",
    "details": {}
  },
  {
    "timestamp": "2025-07-01T22:56:39.666570",
    "user": "system",
    "activity": "Navigated to: Manajemen Data Obat",
    "details": {}
  }
]